[
  {
    "BallingDrum": "230-03-1",
    "Mcx027Tag": "DI613132",
    "Mcx030Tag": "DI613592",
    "Sp027Tag": "S013X025",
    "Ai027Tag": "AI613001",
    "Ai030Tag": "AI613000",
    "Pa030Tag": "PA613000"
  },
  {
    "BallingDrum": "230-03-2",
    "Mcx027Tag": "DI613141",
    "Mcx030Tag": "DI613595",
    "Sp027Tag": "S013X035",
    "Ai027Tag": "AI613007",
    "Ai030Tag": "AI613006",
    "Pa030Tag": "PA613002"
  },
  {
    "BallingDrum": "230-03-3",
    "Mcx027Tag": "DI613148",
    "Mcx030Tag": "DI613598",
    "Sp027Tag": "S013X045",
    "Ai027Tag": "AI613013",
    "Ai030Tag": "AI613012",
    "Pa030Tag": "PA613004"
  },
  {
    "BallingDrum": "230-03-4",
    "Mcx027Tag": "DI613157",
    "Mcx030Tag": "DI613601",
    "Sp027Tag": "S013X053",
    "Ai027Tag": "AI613019",
    "Ai030Tag": "AI613018",
    "Pa030Tag": "PA613006"
  },
  {
    "BallingDrum": "230-04-1",
    "Mcx027Tag": "DI603092",
    "Mcx030Tag": "DI603214",
    "Sp027Tag": "S003X075",
    "Ai027Tag": "AI603001",
    "Ai030Tag": "AI603000",
    "Pa030Tag": "PA601001"
  },
  {
    "BallingDrum": "230-04-2",
    "Mcx027Tag": "DI603108",
    "Mcx030Tag": "DI603230",
    "Sp027Tag": "S003X085",
    "Ai027Tag": "AI603007",
    "Ai030Tag": "AI603006",
    "Pa030Tag": "PA601003"
  },
  {
    "BallingDrum": "230-04-3",
    "Mcx027Tag": "DI603124",
    "Mcx030Tag": "DI603246",
    "Sp027Tag": "S003X215",
    "Ai027Tag": "AI603030",
    "Ai030Tag": "AI601012",
    "Pa030Tag": "PA601005"
  },
  {
    "BallingDrum": "230-04-4",
    "Mcx027Tag": "DI603140",
    "Mcx030Tag": "DI603262",
    "Sp027Tag": "S003X225",
    "Ai027Tag": "AI603031",
    "Ai030Tag": "AI603012",
    "Pa030Tag": "PA601007"
  },
  {
    "BallingDrum": "230-04-5",
    "Mcx027Tag": "DI601124",
    "Mcx030Tag": "DI601151",
    "Sp027Tag": "S003X235",
    "Ai027Tag": "AI603032",
    "Ai030Tag": "AI601013",
    "Pa030Tag": "PA601009"
  },
  {
    "BallingDrum": "230-05-1",
    "Mcx027Tag": "DI605092",
    "Mcx030Tag": "DI605149",
    "Sp027Tag": "S005X043",
    "Ai027Tag": "AI605001",
    "Ai030Tag": "AI605000",
    "Pa030Tag": "PA602001"
  },
  {
    "BallingDrum": "230-05-2",
    "Mcx027Tag": "DI605108",
    "Mcx030Tag": "DI605165",
    "Sp027Tag": "S005X053",
    "Ai027Tag": "AI605007",
    "Ai030Tag": "AI605006",
    "Pa030Tag": "PA602003"
  },
  {
    "BallingDrum": "230-05-3",
    "Mcx027Tag": "DI605124",
    "Mcx030Tag": "DI605181",
    "Sp027Tag": "S005X063",
    "Ai027Tag": "AI605013",
    "Ai030Tag": "AI605012",
    "Pa030Tag": "PA602005"
  },
  {
    "BallingDrum": "230-05-4",
    "Mcx027Tag": "DI605140",
    "Mcx030Tag": "DI605197",
    "Sp027Tag": "S005X203",
    "Ai027Tag": "AI605036",
    "Ai030Tag": "AI605018",
    "Pa030Tag": "PA602007"
  },
  {
    "BallingDrum": "230-05-5",
    "Mcx027Tag": "DI602108",
    "Mcx030Tag": "DI602117",
    "Sp027Tag": "S005X213",
    "Ai027Tag": "AI605037",
    "Ai030Tag": "AI605017",
    "Pa030Tag": "PA602009"
  },
  {
    "BallingDrum": "230-06-1",
    "Mcx027Tag": "DI803020",
    "Mcx030Tag": "DI803066",
    "Sp027Tag": "S011X011",
    "Ai027Tag": "AI811000",
    "Ai030Tag": "AI811001",
    "Pa030Tag": "PA811010"
  },
  {
    "BallingDrum": "230-06-2",
    "Mcx027Tag": "DI803110",
    "Mcx030Tag": "DI803156",
    "Sp027Tag": "S011X021",
    "Ai027Tag": "AI811006",
    "Ai030Tag": "AI811007",
    "Pa030Tag": "PA811011"
  },
  {
    "BallingDrum": "230-06-3",
    "Mcx027Tag": "DI803200",
    "Mcx030Tag": "DI803246",
    "Sp027Tag": "S011X031",
    "Ai027Tag": "AI811012",
    "Ai030Tag": "AI811013",
    "Pa030Tag": "PA811012"
  },
  {
    "BallingDrum": "230-06-4",
    "Mcx027Tag": "DI83X020",
    "Mcx030Tag": "DI83X066",
    "Sp027Tag": "S011X041",
    "Ai027Tag": "AI811018",
    "Ai030Tag": "AI811019",
    "Pa030Tag": "PA811013"
  },
  {
    "BallingDrum": "230-06-5",
    "Mcx027Tag": "DI83X110",
    "Mcx030Tag": "DI83X156",
    "Sp027Tag": "S011X051",
    "Ai027Tag": "AI811024",
    "Ai030Tag": "AI811025",
    "Pa030Tag": "PA811014"
  },
  {
    "BallingDrum": "230-07-1",
    "Mcx027Tag": "DI805020",
    "Mcx030Tag": "DI805066",
    "Sp027Tag": "S013X011",
    "Ai027Tag": "AI813006",
    "Ai030Tag": "AI813007",
    "Pa030Tag": "PA813010"
  },
  {
    "BallingDrum": "230-07-2",
    "Mcx027Tag": "DI805110",
    "Mcx030Tag": "DI805156",
    "Sp027Tag": "S013X021",
    "Ai027Tag": "AI813010",
    "Ai030Tag": "AI813011",
    "Pa030Tag": "PA813011"
  },
  {
    "BallingDrum": "230-07-3",
    "Mcx027Tag": "DI805200",
    "Mcx030Tag": "DI805246",
    "Sp027Tag": "S013X031",
    "Ai027Tag": "AI813014",
    "Ai030Tag": "AI813015",
    "Pa030Tag": "PA813012"
  },
  {
    "BallingDrum": "230-07-4",
    "Mcx027Tag": "DI85X020",
    "Mcx030Tag": "DI85X066",
    "Sp027Tag": "S013X041",
    "Ai027Tag": "AI813018",
    "Ai030Tag": "AI813019",
    "Pa030Tag": "PA813013"
  },
  {
    "BallingDrum": "230-07-5",
    "Mcx027Tag": "DI85X110",
    "Mcx030Tag": "DI85X156",
    "Sp027Tag": "S013X051",
    "Ai027Tag": "AI813022",
    "Ai030Tag": "AI813023",
    "Pa030Tag": "PA813014"
  }

]

